CHANGES.md
LICENSE
MANIFEST.in
README.md
setup.py
extract_dtb/__init__.py
extract_dtb/extract_dtb.py
extract_dtb.egg-info/PKG-INFO
extract_dtb.egg-info/SOURCES.txt
extract_dtb.egg-info/dependency_links.txt
extract_dtb.egg-info/entry_points.txt
extract_dtb.egg-info/not-zip-safe
extract_dtb.egg-info/top_level.txt