Metadata-Version: 2.1
Name: extract-dtb
Version: 1.2.1
Summary: Tool to split a kernel image with appended dtbs into separated kernel and dtb files.
Home-page: https://github.com/PabloCastellano/extract-dtb/
Author: Pablo Castellano
Author-email: pablo@anche.no
License: GPLv3+
Download-URL: https://github.com/PabloCastellano/extract-dtb/archive/master.zip
Keywords: dtb,android,kernel
Platform: UNKNOWN
Classifier: Programming Language :: Python :: 3
Classifier: License :: OSI Approved :: GNU General Public License v3 or later (GPLv3+)
Classifier: Topic :: Software Development :: Embedded Systems
Classifier: Topic :: Software Development :: Version Control :: Git
